Metadata-Version: 2.1
Name: report_builder_vss
Version: 0.0.4
Summary: An application that helps to generate a report of the results of Formula 1 races
Project-URL: Homepage, https://git.foxminded.ua/foxstudent103933/task6/
Author-email: vla_ster <sterinbiz@gmail.com>
License-File: LICENSE
Classifier: License :: OSI Approved :: MIT License
Classifier: Operating System :: OS Independent
Classifier: Programming Language :: Python :: 3
Requires-Python: >=3.7
